lhs/__init__.py
lhs/dist.py
lhs/sample.py
lhs-0.4.2.dist-info/METADATA
lhs-0.4.2.dist-info/WHEEL
lhs-0.4.2.dist-info/licenses/LICENSE
lhs-0.4.2.dist-info/RECORD
