Metadata-Version: 2.3
Name: lhs
Version: 0.4.2
Summary: Latin hypercube sampler for scenario modelling
Project-URL: homepage, https://bitbucket.org/robmoss/latin-hypercube-sampler/
Project-URL: repository, https://bitbucket.org/robmoss/latin-hypercube-sampler/
Project-URL: documentation, https://lhs.readthedocs.io/en/latest/
Project-URL: changelog, https://lhs.readthedocs.io/en/latest/changelog.html
Author-email: Rob Moss <rgmoss@unimelb.edu.au>
Maintainer-email: Rob Moss <rgmoss@unimelb.edu.au>
License: Copyright (c) 2020-24, Rob Moss
License-File: LICENSE
Classifier: Development Status :: 4 - Beta
Classifier: Intended Audience :: Science/Research
Classifier: License :: OSI Approved :: BSD License
Classifier: Operating System :: OS Independent
Classifier: Programming Language :: Python
Classifier: Programming Language :: Python :: 3
Classifier: Topic :: Scientific/Engineering :: Mathematics
Requires-Python: >=3.8
Requires-Dist: numpy>=1.17
Requires-Dist: scipy~=1.4
Provides-Extra: tests
Requires-Dist: pytest; extra == 'tests'
Requires-Dist: pytest-cov~=4.0; extra == 'tests'
